cleantweet/CleanTweet.py
cleantweet/DiagramTweet.py
cleantweet/InferenceTweet.py
cleantweet/PredictionTweet.py
cleantweet/SaveTweet.py
cleantweet/SentimentTweet.py
cleantweet/StatsTweet.py
cleantweet/SyntheticTweet.py
cleantweet/__init__.py
tests/__init__.py
tests/cleantweet_tests.py
tests/diagramtweets_tests.py
tests/inferencetweets_tests.py
tests/predictiontweet_tests.py
tests/sentimenttweet_tests.py
tests/statstweet_tests.py
tests/synthetictweet_tests.py
cleantweet-2.0.3.dist-info/METADATA
cleantweet-2.0.3.dist-info/WHEEL
cleantweet-2.0.3.dist-info/top_level.txt
cleantweet-2.0.3.dist-info/RECORD
