Metadata-Version: 2.1
Name: cleantweet
Version: 2.0.3
Summary: a python library to clean textual data fetched from API's
Home-page: https://cleantweet.org/
Author: Lare Adeola
Author-email: lare@cleantweet.org
License: MIT
Classifier: Intended Audience :: Developers
Classifier: License :: OSI Approved :: MIT License
Classifier: Programming Language :: Python
Classifier: Programming Language :: Python :: 3
Classifier: Programming Language :: Python :: 3.6
Classifier: Programming Language :: Python :: 3.7
Classifier: Programming Language :: Python :: 3.8
Classifier: Programming Language :: Python :: 3.9
Classifier: Operating System :: OS Independent
Requires-Python: >=3.6
Requires-Dist: nltk
Requires-Dist: pandas
Requires-Dist: matplotlib
Requires-Dist: wordcloud
